unusualwhales/__init__.py
unusualwhales/api/__init__.py
unusualwhales/api/congress/__init__.py
unusualwhales/api/congress/get_late_reports.py
unusualwhales/api/congress/get_reports.py
unusualwhales/api/congress/get_trades.py
unusualwhales/api/congress/get_trades_by_member.py
unusualwhales/api/contract/__init__.py
unusualwhales/api/contract/get_price_history.py
unusualwhales/api/darkpool/__init__.py
unusualwhales/api/darkpool/get_trades_by_date.py
unusualwhales/api/darkpool/get_trades_by_ticker.py
unusualwhales/api/earnings/__init__.py
unusualwhales/api/earnings/get_afterhours.py
unusualwhales/api/earnings/get_premarket.py
unusualwhales/api/earnings/get_ticker_earnings.py
unusualwhales/api/etfs/__init__.py
unusualwhales/api/etfs/get_holdings.py
unusualwhales/api/etfs/get_info.py
unusualwhales/api/etfs/get_sector_country_weights.py
unusualwhales/api/etfs/get_ticker_exposure.py
unusualwhales/api/flow/__init__.py
unusualwhales/api/flow/get_contract_flow.py
unusualwhales/api/flow/get_flow_by_expiry.py
unusualwhales/api/flow/get_flow_by_strike.py
unusualwhales/api/flow/get_full_tape.py
unusualwhales/api/flow/get_order_flow.py
unusualwhales/api/flow/get_ticker_order_flow.py
unusualwhales/api/flow/get_unusual_flow_alerts.py
unusualwhales/api/market/__init__.py
unusualwhales/api/market/get_economic_calendar.py
unusualwhales/api/market/get_fda_calendar.py
unusualwhales/api/market/get_holidays.py
unusualwhales/api/market/get_imbalances.py
unusualwhales/api/market/get_insider_trades.py
unusualwhales/api/market/get_market_options_volume.py
unusualwhales/api/market/get_market_tide.py
unusualwhales/api/market/get_market_tide_by_etf.py
unusualwhales/api/market/get_open_interest_change.py
unusualwhales/api/market/get_sector_stats.py
unusualwhales/api/market/get_spike.py
unusualwhales/api/screener/__init__.py
unusualwhales/api/screener/get_analyst_ratings.py
unusualwhales/api/screener/get_option_contracts.py
unusualwhales/api/screener/get_stocks.py
unusual_whales_api_client-1.3.dist-info/LICENSE
unusual_whales_api_client-1.3.dist-info/METADATA
unusual_whales_api_client-1.3.dist-info/WHEEL
unusual_whales_api_client-1.3.dist-info/RECORD
